certbot_dns_freedns/__init__.py
certbot_dns_freedns/dns_freedns.py
certbot_dns_freedns-0.2.0.dist-info/LICENSE.txt
certbot_dns_freedns-0.2.0.dist-info/METADATA
certbot_dns_freedns-0.2.0.dist-info/WHEEL
certbot_dns_freedns-0.2.0.dist-info/entry_points.txt
certbot_dns_freedns-0.2.0.dist-info/top_level.txt
certbot_dns_freedns-0.2.0.dist-info/RECORD
