Metadata-Version: 2.1
Name: certbot-dns-freedns
Version: 0.2.0
Summary: FreeDNS Authenticator plugin for Certbot
Home-page: https://github.com/schleuss/certbot-dns-freedns
Author: Rafael Schleuss
Author-email: Rafael Schleuss <rschleuss@gmail.com>
License: Permission is hereby granted, free of charge, to any person obtaining
Project-URL: Homepage, https://github.com/schleuss/certbot_dns_freedns
Keywords: FreeDNS,Certbot
Classifier: License :: OSI Approved :: MIT License
Classifier: Programming Language :: Python
Classifier: Programming Language :: Python :: 3
Requires-Python: >=3.0
License-File: LICENSE.txt
Requires-Dist: acme >=1.22.0
Requires-Dist: certbot >=1.22.0
Requires-Dist: setuptools
Requires-Dist: requests >=2.26.0
Requires-Dist: bs4 >=0.0.1
